LICENSE.txt
README.txt
setup.py
DryhbSuport/__init__.py
DryhbSupport.egg-info/PKG-INFO
DryhbSupport.egg-info/SOURCES.txt
DryhbSupport.egg-info/dependency_links.txt
DryhbSupport.egg-info/top_level.txt